higeki/__init__.py
higeki-0.1.0.dist-info/WHEEL
higeki-0.1.0.dist-info/METADATA
higeki-0.1.0.dist-info/RECORD
