Metadata-Version: 2.1
Name: higeki
Version: 0.1.0
Summary: 悲劇
Author: Yevgnen Koh
Author-email: wherejoystarts@gmail.com
Requires-Python: >=3.9,<4.0
Classifier: Programming Language :: Python :: 3
Classifier: Programming Language :: Python :: 3.9
